speedrecorder-0.1.dist-info/WHEEL
speedrecorder-0.1.dist-info/DESCRIPTION.rst
speedrecorder-0.1.dist-info/metadata.json
speedrecorder-0.1.dist-info/METADATA
speedrecorder-0.1.dist-info/RECORD
speedrecorder-0.1.dist-info/top_level.txt
speedrecorder/__init__.py
