Metadata-Version: 2.0
Name: speedrecorder
Version: 0.1
Summary: A function that records your internet speed
Home-page: https://github.com/rweyant/speedtest-cli
Author: UNKNOWN
Author-email: UNKNOWN
License: UNKNOWN
Platform: UNKNOWN
Requires-Dist: ipgetter
Requires-Dist: requests
